examples/aerodynamic_car_design/main_shapenetcar.py
examples/aerodynamic_drag_pred/ppfno/inference.py
examples/aerodynamic_drag_pred/ppfno/inferenceDataPreprocessSmesh.py
examples/aerodynamic_drag_pred/ppfno/inferenceDataPreprocessVmesh.py
examples/aerodynamic_drag_pred/ppfno/inference_server.py
examples/aerodynamic_drag_pred/ppfno/refine.py
examples/aerodynamic_drag_pred/ppfno/train.py
examples/aerodynamic_drag_pred/ppfno/trainDataPreprocess.py
examples/aerodynamics/ppkan/average_meter.py
examples/aerodynamics/ppkan/dataset_creation_sim.py
examples/aerodynamics/ppkan/main.py
examples/aerodynamics/ppkan/mlp.py
examples/aerodynamics/ppkan/visualization.py
examples/darcyflow/ppdeeponet/pimultionet.py
examples/darcyflow/ppdeeponet/Solvers/Module.py
examples/darcyflow/ppdeeponet/Solvers/PIDeepONet.py
examples/darcyflow/ppdeeponet/Solvers/PIMultiONet.py
examples/darcyflow/ppdeeponet/Solvers/soap.py
examples/darcyflow/ppdeeponet/Utils/GenPoints.py
examples/darcyflow/ppdeeponet/Utils/GenPoints_Time.py
examples/darcyflow/ppdeeponet/Utils/Grad.py
examples/darcyflow/ppdeeponet/Utils/Losses.py
examples/darcyflow/ppdeeponet/Utils/Normalizer.py
examples/darcyflow/ppdeeponet/Utils/PlotFigure.py
examples/darcyflow/ppdeeponet/Utils/RBFInterpolatorMesh.py
examples/darcyflow/ppdeeponet/Utils/TestFun_ParticleWNN.py
examples/darcyflow/ppdeeponet/Utils/utils.py
examples/darcyflow/ppkan/main.py
examples/darcyflow/ppkan/mlp.py
examples/flow_field_prediction/ppdiffusion/train.py
examples/flow_field_prediction/ppdiffusion/datamodules/__init__.py
examples/flow_field_prediction/ppdiffusion/datamodules/physical.py
examples/flow_field_prediction/ppdiffusion/utils/__init__.py
examples/flow_field_prediction/ppdiffusion/utils/average_meter.py
examples/flow_field_prediction/ppdiffusion/utils/functions.py
ppcfd/__init__.py
ppcfd/data/__init__.py
ppcfd/data/downloader.py
ppcfd/data/loader.py
ppcfd/data/shapenetcar_datamodule.py
ppcfd/data/parser/__init__.py
ppcfd/data/parser/base_parser.py
ppcfd-0.3.0.dist-info/METADATA
ppcfd-0.3.0.dist-info/WHEEL
ppcfd-0.3.0.dist-info/top_level.txt
ppcfd-0.3.0.dist-info/RECORD
