Metadata-Version: 2.4
Name: ppcfd
Version: 0.3.0
Summary: PaddleCFD is a deep learning toolkit for surrogate modeling, equation discovery, shape optimization and flow-control strategy discovery in the field of fluid mechanics.
Home-page: https://github.com/PaddlePaddle/PaddleCFD
Author: AI4S@PaddlePaddle
Author-email: "AI4S@PaddlePaddle" <paddlescience@baidu.com>
License: Apache-2.0
Project-URL: Homepage, https://github.com/PaddlePaddle/PaddleCFD
Project-URL: Issues, https://github.com/PaddlePaddle/PaddleCFD/issues
Classifier: Programming Language :: Python :: 3
Classifier: Operating System :: OS Independent
Requires-Python: >=3.10
Requires-Dist: colorlog
Requires-Dist: configmypy
Requires-Dist: einops
Requires-Dist: fastapi~=0.115.12
Requires-Dist: gmsh
Requires-Dist: h5py~=3.11.0
Requires-Dist: hydra-core
Requires-Dist: imageio
Requires-Dist: matplotlib
Requires-Dist: meshio==5.3.4
Requires-Dist: numpy<2.0.0,>=1.20.0
Requires-Dist: opt-einsum
Requires-Dist: pandas~=2.2.1
Requires-Dist: pydantic>=2.5.0
Requires-Dist: pyevtk
Requires-Dist: pymeshlab
Requires-Dist: pynvml
Requires-Dist: pyvista
Requires-Dist: pyyaml
Requires-Dist: requests
Requires-Dist: ruamel.yaml
Requires-Dist: scienceplots
Requires-Dist: scikit-learn<1.5.0
Requires-Dist: scikit-optimize
Requires-Dist: scipy~=1.14.1
Requires-Dist: seaborn
Requires-Dist: numpy-stl
Requires-Dist: sympy
Requires-Dist: tabulate
Requires-Dist: tqdm
Requires-Dist: typing-extensions
Requires-Dist: uvicorn~=0.34.2
Requires-Dist: wget
Requires-Dist: xarray
Requires-Dist: xskillscore
Requires-Dist: zarr
Dynamic: author
Dynamic: home-page
Dynamic: requires-python
